design.sv
module mux4to1_if (
    input  wire [1:0] sel,
    input  wire [3:0] in,
    output reg        out
);
    always @(*) begin
        if (sel == 2'b00)
            out = in[0];
        else if (sel == 2'b01)
            out = in[1];
        else if (sel == 2'b10)
            out = in[2];
        else
            out = in[3];
    end
endmodule

testbench.sv

module tb_mux4to1;

    reg [1:0] sel;
    reg [3:0] in;

    wire out_assign;
    wire out_case;
    wire out_if;


    mux4to1_if mux_if (
        .sel(sel),
        .in(in),
        .out(out_if)
    );

    initial begin
      $dumpfile("mux4to1_if.vcd");
      $dumpvars;
        $display("Time\tSel\tIn\tAssign\tCase\tIf");
        $monitor("%0t\t%02b\t%b\t%b\t%b\t%b", 
                  $time, sel, in, out_if);

        in = 4'b1010;  

        sel = 2'b00; #10;
        sel = 2'b01; #10;
        sel = 2'b10; #10;
        sel = 2'b11; #10;

        in = 4'b0101;  
        sel = 2'b00; #10;
        sel = 2'b01; #10;
        sel = 2'b10; #10;
        sel = 2'b11; #10;

        $finish;
    end

endmodule

mux4to1_if.vcd
$date
	Thu Aug  7 09:31:35 2025
$end
$version
	Icarus Verilog
$end
$timescale
	1s
$end
$scope module tb_mux4to1 $end
$var wire 1 ! out_if $end
$var reg 4 " in [3:0] $end
$var reg 2 # sel [1:0] $end
$scope module mux_if $end
$var wire 4 $ in [3:0] $end
$var wire 2 % sel [1:0] $end
$var reg 1 ! out $end
$upscope $end
$upscope $end
$enddefinitions $end
$comment Show the parameter values. $end
$dumpall
$end
#0
$dumpvars
b0 %
b1010 $
b0 #
b1010 "
0!
$end
#10
1!
b1 #
b1 %
#20
0!
b10 #
b10 %
#30
1!
b11 #
b11 %
#40
b0 #
b0 %
b101 "
b101 $
#50
0!
b1 #
b1 %
#60
1!
b10 #
b10 %
#70
0!
b11 #
b11 %
